mop_utils/__init__.py
mop_utils/base_model_wrapper.py
mop_utils/constant.py
mop_utils/inference_wrapper.py
mop_utils_test-1.8.1.dist-info/METADATA
mop_utils_test-1.8.1.dist-info/WHEEL
mop_utils_test-1.8.1.dist-info/top_level.txt
mop_utils_test-1.8.1.dist-info/RECORD
